{
  "resetPassword": {
    "title": "Set a new password",
    "description": "Choose a strong password for your account.",
    "newPasswordLabel": "New password",
    "newPasswordPlaceholder": "Min. 8 characters",
    "confirmPasswordLabel": "Confirm new password",
    "confirmPasswordPlaceholder": "Repeat your new password",
    "resetting": "Resetting…",
    "resetButton": "Reset password",
    "backToLogin": "Back to login",
    "loading": "Loading…",
    "errorInvalidLink": "Invalid reset link.",
    "errorPasswordMismatch": "Passwords do not match.",
    "errorPasswordTooShort": "Password must be at least 8 characters.",
    "errorExpiredLink": "Invalid or expired reset link.",
    "successMessage": "Password reset! Please log in."
  }
}
